{
  "EX1_169": [
    2,
    0
  ],
  "CS2_008": [
    2,
    0
  ],
  "CS2_005": [
    2,
    0
  ],
  "EX1_161": [
    1,
    0
  ],
  "CS2_009": [
    2,
    0
  ],
  "EX1_160": [
    2,
    0
  ],
  "CS2_013": [
    2,
    1
  ],
  "EX1_154": [
    1,
    0
  ],
  "GVG_030": [
    2,
    0
  ],
  "CS2_007": [
    2,
    2
  ],
  "EX1_155": [
    2,
    0
  ],
  "CS2_011": [
    2,
    0
  ],
  "FP1_019": [
    2,
    0
  ],
  "EX1_158": [
    2,
    0
  ],
  "CS2_012": [
    2,
    0
  ],
  "NEW1_007": [
    0,
    1
  ],
  "EX1_165": [
    2,
    0
  ],
  "EX1_173": [
    2,
    0
  ],
  "EX1_178": [
    0,
    1
  ],
  "CS2_232": [
    2,
    0
  ],
  "CS2_084": [
    2,
    0
  ],
  "DS1_185": [
    2,
    0
  ],
  "DS1_184": [
    2,
    2
  ],
  "DS1_175": [
    2,
    0
  ],
  "FP1_011": [
    2,
    0
  ],
  "EX1_610": [
    2,
    0
  ],
  "EX1_544": [
    1,
    0
  ],
  "EX1_611": [
    1,
    0
  ],
  "EX1_609": [
    2,
    0
  ],
  "NEW1_031": [
    2,
    0
  ],
  "EX1_617": [
    1,
    0
  ],
  "EX1_539": [
    2,
    0
  ],
  "EX1_538": [
    2,
    0
  ],
  "DS1_183": [
    2,
    0
  ],
  "DS1_070": [
    2,
    0
  ],
  "GVG_046": [
    1,
    0
  ],
  "CS2_237": [
    2,
    0
  ],
  "DS1_178": [
    2,
    0
  ],
  "EX1_534": [
    1,
    0
  ]
}